quiz_me/__init__.py
quiz_me/config.py
quiz_me/models.py
quiz_me/states.py
quiz_me/flows/CLAUDE.md
quiz_me/flows/__init__.py
quiz_me/flows/multi.py
quiz_me/flows/single.py
quiz_me/nodes/CLAUDE.md
quiz_me/nodes/__init__.py
quiz_me/nodes/finalize_question.py
quiz_me/nodes/generate.py
quiz_me/nodes/generate_from_spec.py
quiz_me/nodes/improve.py
quiz_me/nodes/plan.py
quiz_me/nodes/supervise.py
quiz_me/nodes/supervise_multi.py
quiz_me/prompts/CLAUDE.md
quiz_me/prompts/_quality_guidelines.jinja
quiz_me/prompts/generate_question.jinja
quiz_me/prompts/plan_questions.jinja
quiz_me/prompts/supervise_question.jinja
quiz_me-0.1.1.dist-info/METADATA
quiz_me-0.1.1.dist-info/WHEEL
quiz_me-0.1.1.dist-info/licenses/LICENSE
quiz_me-0.1.1.dist-info/RECORD
