Metadata-Version: 2.4
Name: quiz-me
Version: 0.1.1
Summary: AI-powered question generation library using Langgraph flows
Project-URL: Homepage, https://github.com/lfnovo/quiz-me
Project-URL: Repository, https://github.com/lfnovo/quiz-me
Project-URL: Issues, https://github.com/lfnovo/quiz-me/issues
Author-email: Luis Novo <luis@lfnovo.com>
License: MIT
License-File: LICENSE
Keywords: ai,education,educational-technology,langchain,langgraph,llm,question-generation,questions,quiz
Classifier: Development Status :: 4 - Beta
Classifier: Intended Audience :: Developers
Classifier: Intended Audience :: Education
Classifier: License :: OSI Approved :: MIT License
Classifier: Programming Language :: Python :: 3
Classifier: Programming Language :: Python :: 3.10
Classifier: Programming Language :: Python :: 3.11
Classifier: Programming Language :: Python :: 3.12
Classifier: Topic :: Education
Classifier: Topic :: Scientific/Engineering :: Artificial Intelligence
Classifier: Topic :: Software Development :: Libraries :: Python Modules
Requires-Python: >=3.10
Requires-Dist: ai-prompter
Requires-Dist: langchain-core>=0.3.0
Requires-Dist: langgraph>=1.0.0
Requires-Dist: pydantic>=2.10
Provides-Extra: dev
Requires-Dist: esperanto; extra == 'dev'
Requires-Dist: ipykernel; extra == 'dev'
Requires-Dist: pytest-asyncio>=0.24; extra == 'dev'
Requires-Dist: pytest>=8.0; extra == 'dev'
